{
    "label_tree": {
        "type": "tree",
        "directed": true,
        "nodes": [],
        "edges": []
    },
    "label_groups": [
        {
            "_id": "64641a255f40ae8de0f15b76",
            "name": "labels",
            "label_ids": [
                "0"
            ],
            "relation_type": "EXCLUSIVE"
        }
    ],
    "all_labels": {
        "0": {
            "_id": "0",
            "name": "kiemgetal",
            "color": {
                "red": 213,
                "green": 91,
                "blue": 210,
                "alpha": 255
            },
            "hotkey": "",
            "domain": "INSTANCE_SEGMENTATION",
            "creation_date": "2023-05-17T00:04:09.847000",
            "is_empty": false,
            "is_anomalous": false
        }
    }
}